src/command_line.py
src/constants.py
src/lotus.xlaunch
src/lotusAnimations.py
src/lotusButtons.py
src/lotusCalender.py
src/lotusCore.py
src/lotusFloating.py
src/lotusHelp.py
src/lotusHub.py
src/lotusNotes.py
src/lotusPrevious.py
src/lotusSettings.py
src/lotusUtils.py
src/wsl.py
src/assets/Clear.png
src/assets/Color_Indicator.png
src/assets/Color_Wheel.png
src/assets/Eraser.png
src/assets/Highlighter.png
src/assets/Home.png
src/assets/Lato-Regular.ttf
src/assets/Pen.png
src/assets/PenEraserCursor.png
src/assets/Redo.png
src/assets/Undo.png
src/assets/help.png
src/assets/help_darker.png
src/assets/help_lotus_home.JPG
src/assets/help_lotus_notes_2.png
src/assets/help_new_notes_1.JPG
src/assets/help_new_notes_10.JPG
src/assets/help_new_notes_2.JPG
src/assets/help_new_notes_3.1.JPG
src/assets/help_new_notes_3.2.JPG
src/assets/help_new_notes_3.3.JPG
src/assets/help_new_notes_3.JPG
src/assets/help_new_notes_4.JPG
src/assets/help_new_notes_5.JPG
src/assets/help_new_notes_6.JPG
src/assets/help_new_notes_7.JPG
src/assets/help_new_notes_8.JPG
src/assets/help_new_notes_9.JPG
src/assets/help_previous_notes_1.JPG
src/assets/help_previous_notes_2.JPG
src/assets/help_schedule_1.JPG
src/assets/help_schedule_2.JPG
src/assets/help_schedule_3.JPG
src/assets/help_schedule_4.JPG
src/assets/help_schedule_5.JPG
src/assets/help_schedule_6.JPG
src/assets/help_schedule_7.JPG
src/assets/help_schedule_8.JPG
src/assets/help_schedule_9.JPG
src/assets/logo_black.png
src/assets/lotus.png
src/assets/lotusLarge.png
src/assets/lotusSmall.png
src/assets/newNote.png
src/assets/newNoteDarker.png
src/assets/previousNotes.png
src/assets/previousNotesDarker.png
src/assets/schedule.png
src/assets/scheduleDarker.png
src/assets/settings.png
src/assets/settings_darker.png
src/assets/time_date.png
lotus_notes-2.0.1.dist-info/LICENSE.txt
lotus_notes-2.0.1.dist-info/METADATA
lotus_notes-2.0.1.dist-info/WHEEL
lotus_notes-2.0.1.dist-info/entry_points.txt
lotus_notes-2.0.1.dist-info/top_level.txt
lotus_notes-2.0.1.dist-info/RECORD
