Metadata-Version: 2.1
Name: lotus-notes
Version: 2.0.1
Summary: Lotus - A hand-written notes application with scheduler.
Home-page: https://github.com/nipunaw/Lotus/tree/design-prototype
Author: Nipuna Weerapperuma, Spencer Bass, David Jaworski, Carlos Morales-Diaz, & Hannah Williams
License: MIT
Platform: UNKNOWN
Requires-Python: >=3.7
Requires-Dist: opencv-python-headless
Requires-Dist: PyQt5
Requires-Dist: wsl
Requires-Dist: wheel
Requires-Dist: pytesseract
